btcorerpc/__init__.py
btcorerpc/__version__.py
btcorerpc/exceptions.py
btcorerpc/logfactory.py
btcorerpc/rpc.py
btcorerpc/util.py
btcorerpc-0.2.0.dist-info/licenses/LICENSE
btcorerpc-0.2.0.dist-info/METADATA
btcorerpc-0.2.0.dist-info/WHEEL
btcorerpc-0.2.0.dist-info/top_level.txt
btcorerpc-0.2.0.dist-info/RECORD
